graph_nd/__init__.py
graph_nd/graphrag/__init__.py
graph_nd/graphrag/graph_data.py
graph_nd/graphrag/graph_records.py
graph_nd/graphrag/graph_schema.py
graph_nd/graphrag/graphrag.py
graph_nd/graphrag/prompt_templates.py
graph_nd/graphrag/schema_from_db_utils.py
graph_nd/graphrag/source_metadata.py
graph_nd/graphrag/table_mapping.py
graph_nd/graphrag/utils.py
graph_nd-0.0.3.dist-info/METADATA
graph_nd-0.0.3.dist-info/WHEEL
graph_nd-0.0.3.dist-info/RECORD
