Metadata-Version: 2.3
Name: graph_nd
Version: 0.0.3
Summary: A Python package for building powerful end-to-end agentic GraphRAG systems with a simple, intuitive API
Author: Zach Blumenfeld
Author-email: zblumenf@gmail.com
Requires-Python: >=3.10
Classifier: Programming Language :: Python :: 3
Classifier: Programming Language :: Python :: 3.10
Classifier: Programming Language :: Python :: 3.11
Classifier: Programming Language :: Python :: 3.12
Classifier: Programming Language :: Python :: 3.13
Requires-Dist: PyPDF2
Requires-Dist: PyYAML
Requires-Dist: langchain-core
Requires-Dist: langchain-openai
Requires-Dist: langgraph
Requires-Dist: neo4j
Requires-Dist: nest-asyncio
Requires-Dist: pandas
Requires-Dist: pydantic
Requires-Dist: python-dotenv
Requires-Dist: tqdm
Project-URL: Documentation, https://graph-nd.readthedocs.io/
Project-URL: Repository, https://github.com/zach-blumenfeld/graph-nd
